lsbi/__init__.py
lsbi/_version.py
lsbi/model.py
lsbi/stats.py
lsbi/utils.py
lsbi-0.12.3.dist-info/LICENSE
lsbi-0.12.3.dist-info/METADATA
lsbi-0.12.3.dist-info/WHEEL
lsbi-0.12.3.dist-info/top_level.txt
lsbi-0.12.3.dist-info/RECORD
